date_extractor_mds/__init__.py
date_extractor_mds/date_extractor_mds.py
date_extractor_mds-1.2.1.dist-info/LICENSE
date_extractor_mds-1.2.1.dist-info/METADATA
date_extractor_mds-1.2.1.dist-info/WHEEL
date_extractor_mds-1.2.1.dist-info/RECORD
