Metadata-Version: 2.3
Name: date_extractor_mds
Version: 1.2.1
Summary: A package for extracting dates!
License: MIT
Author: Rashid Mammadov
Requires-Python: >=3.9,<4.0
Classifier: License :: OSI Approved :: MIT License
Classifier: Programming Language :: Python :: 3
Classifier: Programming Language :: Python :: 3.9
Classifier: Programming Language :: Python :: 3.10
Classifier: Programming Language :: Python :: 3.11
Classifier: Programming Language :: Python :: 3.12
Classifier: Programming Language :: Python :: 3.13
Requires-Dist: pandas (>=2.2.3,<3.0.0)
